{
	"INFANTRY": {"longname": "Infantry",
		"shortname": "Inftry",
		"icon": "",
		"description": "Infantry movement type."
	},
	"MECH": {"longname": "Mech",
		"shortname": "Mech",
		"icon": "",
		"description": "Mech movement type."
	},
	"TIRES": {"longname": "Tires",
		"shortname": "Tires",
		"icon": "",
		"description": "This unit uses tires to move."
	},
	"TREAD": {"longname": "Tread",
		"shortname": "Tread",
		"icon": "",
		"description": "This unit uses treads to move."
	},
	"AIR": {"longname": "Air",
		"shortname": "Air",
		"icon": "",
		"description": "This unit flies through the air."
	},
	"PIPELINE": {"longname": "Pipeline",
		"shortname": "Pipe",
		"icon": "",
		"description": "This unit moves along pipes."
	},
	"SHIPS": {"longname": "Ships",
		"shortname": "Ships",
		"icon": "",
		"description": "This unit sails through sea."
	},
	"TRANSPORT": {"longname": "Transport",
		"shortname": "Trans",
		"icon": "",
		"description": "This unit can stop at shoals."
	},
	"SLIME": {"longname": "Slime",
		"shortname": "Slime",
		"icon": "",
		"description": "This unit is made out of slime."
	}
}